odoo8_addon_l10n_fr_account_tax_unece-8.0.1.0.0-py2.7-nspkg.pth
odoo_addons/l10n_fr_account_tax_unece/post_install.py
odoo_addons/l10n_fr_account_tax_unece/__openerp__.py
odoo_addons/l10n_fr_account_tax_unece/__init__.py
odoo_addons/l10n_fr_account_tax_unece/README.rst
odoo8_addon_l10n_fr_account_tax_unece-8.0.1.0.0.dist-info/top_level.txt
odoo8_addon_l10n_fr_account_tax_unece-8.0.1.0.0.dist-info/WHEEL
odoo8_addon_l10n_fr_account_tax_unece-8.0.1.0.0.dist-info/RECORD
odoo8_addon_l10n_fr_account_tax_unece-8.0.1.0.0.dist-info/metadata.json
odoo8_addon_l10n_fr_account_tax_unece-8.0.1.0.0.dist-info/DESCRIPTION.rst
odoo8_addon_l10n_fr_account_tax_unece-8.0.1.0.0.dist-info/METADATA
odoo8_addon_l10n_fr_account_tax_unece-8.0.1.0.0.dist-info/namespace_packages.txt
